b2btrace
