Metadata-Version: 2.1
Name: b2btrace
Version: 0.0.4
Summary: BAM-to-barcode tracing of sequences
Author: Bence Kover
Author-email: <kover.bence@gmail.com>
Keywords: samtools,singlecell,barcode,bam
Classifier: Development Status :: 1 - Planning
Classifier: Intended Audience :: Science/Research
Classifier: Programming Language :: Python :: 3
Classifier: Operating System :: MacOS :: MacOS X
License-File: LICENSE
Requires-Dist: numpy
Requires-Dist: pandas
Provides-Extra: external
Requires-Dist: samtools; extra == "external"
